[
  {
    "County": "Mombasa",
    "Wards": [
      "Airport",
      "Bamburi",
      "Bofu",
      "Chaani",
      "Changamwe",
      "Frere Town",
      "Jomvu Kuu",
      "Junda",
      "Kadzandani",
      "Kipevu",
      "Kongowea",
      "Likoni",
      "Magogoni",
      "Majengo",
      "Mikindani",
      "Miritini",
      "Mjambere",
      "Mji Wa Kale/Makadara",
      "Mkomani",
      "Mtongwe",
      "Mtopanga",
      "Mwakirunge",
      "Port Reitz",
      "Shanzu",
      "Shika Adabu",
      "Timbwani",
      "Tononoka",
      "Tudor",
      "Ziwa La Ng'Ombe"
    ]
  },
  {
    "County": "Kwale",
    "Wards": [
      "Dzombo",
      "Gombatobongwe",
      "Kinondo",
      "Kubo South",
      "Mkongani",
      "Mwereni",
      "Pongwekikoneni",
      "Ramisi",
      "Tiwi",
      "Tsimba Golini",
      "Ukunda",
      "Vanga",
      "Waa"
    ]
  },
  {
    "County": "Kilifi",
    "Wards": [
      "Adu",
      "Bamba",
      "Chasimba",
      "Dabaso",
      "Ganda",
      "Ganze",
      "Garashi",
      "Gongoni",
      "Jaribuni",
      "Jilore",
      "Junju",
      "Kakuyuni",
      "Kaloleni",
      "Kambe/Ribe",
      "Kayafungo",
      "Kibarani",
      "Magarini",
      "Malindi Town",
      "Marafa",
      "Mariakani",
      "Matsangoni",
      "Mnarani",
      "Mtepeni",
      "Mwanamwinga",
      "Mwarakaya",
      "Mwawesa",
      "Rabai/Kisurutini",
      "Ruruma",
      "Sabaki",
      "Shella",
      "Shimo La Tewa",
      "Sokoke",
      "Sokoni",
      "Tezo",
      "Watamu"
    ]
  },
  {
    "County": "Tana River",
    "Wards": [
      "Bangale",
      "Bura",
      "Chewani",
      "Chewele",
      "Garsen Central",
      "Garsen North",
      "Garsen South",
      "Garsen West",
      "Kinakomba",
      "Kipini East",
      "Kipini West",
      "Madogo",
      "Mikinduni",
      "Sala",
      "Wayu"
    ]
  },
  {
    "County": "Lamu",
    "Wards": [
      "Bahari",
      "Basuba",
      "Faza",
      "Hindi",
      "Hongwe",
      "Kiunga",
      "Mkomani",
      "Mkunumbi",
      "Shella",
      "Witu"
    ]
  },
  {
    "County": "Taita Taveta",
    "Wards": [
      "Bomeni",
      "Bura",
      "Chala",
      "Chawia",
      "Kaloleni",
      "Kasigau",
      "Mahoo",
      "Marungu",
      "Mata",
      "Mboghoni",
      "Mbololo",
      "Mwanda/Mgange",
      "Mwatate",
      "Ngolia",
      "Rong'E",
      "Sagalla",
      "Werugha",
      "Wumingu/Kishushe",
      "Wundanyi/Mbale",
      "Wusi/Kishamba"
    ]
  },
  {
    "County": "Garissa",
    "Wards": [
      "Abakaile",
      "Balambala",
      "Baraki",
      "Benane",
      "Bura",
      "Dadaab",
      "Damajale",
      "Danyere",
      "Dekaharia",
      "Dertu",
      "Fafi",
      "Galbet",
      "Goreale",
      "Hulugho",
      "Iftin",
      "Ijara",
      "Jara Jara",
      "Jarajila",
      "Labasigale",
      "Liboi",
      "Maalimin",
      "Masalani",
      "Modogashe",
      "Nanighi",
      "Sabena",
      "Saka",
      "Sangailu",
      "Sankuri",
      "Township",
      "Waberi"
    ]
  },
  {
    "County": "Wajir",
    "Wards": [
      "Ademasajide",
      "Arbajahan",
      "Barwago",
      "Batalu",
      "Benane",
      "Burder",
      "Bute",
      "Dadaja Bulla",
      "Danaba",
      "Della",
      "Diif",
      "Elben",
      "Eldas",
      "Elnur/Tula Tula",
      "Godoma",
      "Gurar",
      "Habasswein",
      "Hadado/Athibohol",
      "Ibrahim Ure",
      "Khorof/Harar",
      "Korondile",
      "Lagboghol South",
      "Lakoley South/Basir",
      "Malkagufu",
      "Sarman",
      "Tarbaj",
      "Township",
      "Wagalla/Ganyure",
      "Wagberi",
      "Wargadud"
    ]
  },
  {
    "County": "Mandera",
    "Wards": [
      "Alungo Gof",
      "Arabia",
      "Ashabito",
      "Banissa",
      "Bulla Mpya",
      "Dandu",
      "Derkhale",
      "Elwak North",
      "Elwak South",
      "Fino",
      "Gither",
      "Guba",
      "Guticha",
      "Khalalio",
      "Kiliwehiri",
      "Kutulo",
      "Lafey",
      "Lag Sure",
      "Libehia",
      "Malkamari",
      "Morothile",
      "Neboi",
      "Rhamu",
      "Rhamu-Dimtu",
      "Shimbir Fatuma",
      "Takaba",
      "Takaba South",
      "Township",
      "Warankara",
      "Wargudud"
    ]
  },
  {
    "County": "Marsabit",
    "Wards": [
      "Butiye",
      "Dukana",
      "Golbo",
      "Heilu-Manyatta",
      "Illeret",
      "Karare",
      "Kargi/South Horr",
      "Korr/Ngurunit",
      "Laisamis",
      "Log Logo",
      "Loiyangalani",
      "Maikona",
      "Marsabit Central",
      "Moyale Township",
      "North Horr",
      "Obbu",
      "Sagante/Jaldesa",
      "Sololo",
      "Turbi",
      "Uran"
    ]
  },
  {
    "County": "Isiolo",
    "Wards": [
      "Bulla Pesa",
      "Burat",
      "Chari",
      "Cherab",
      "Garbatulla",
      "Kinna",
      "Ngare Mara",
      "Oldonyiro",
      "Sericho",
      "Wabera"
    ]
  },
  {
    "County": "Meru",
    "Wards": [
      "Abogeta East",
      "Abogeta West",
      "Abothuguchi Central",
      "Abothuguchi West",
      "Akachiu",
      "Akirang'Ondu",
      "Akithii",
      "Amwathi",
      "Antuambui",
      "Antubetwe Kiongo",
      "Athiru Gaiti",
      "Athiru Ruujine",
      "Athwana",
      "Igembe East",
      "Igoji East",
      "Igoji West",
      "Kangeta",
      "Kanuni",
      "Karama",
      "Kiagu",
      "Kianjai",
      "Kibirichia",
      "Kiegoi/Antubochiu",
      "Kiguchwa",
      "Kiirua/Naari",
      "Kisima",
      "Maua",
      "Mbeu",
      "Mikinduri",
      "Mitunguu",
      "Municipality",
      "Muthara",
      "Mwanganthia",
      "Naathu",
      "Njia",
      "Nkomo",
      "Nkuene",
      "Ntima East",
      "Ntima West",
      "Ntunene",
      "Nyaki East",
      "Nyaki West",
      "Ruiri/Rwarera",
      "Thangatha",
      "Timau"
    ]
  },
  {
    "County": "Tharaka-Nithi",
    "Wards": [
      "Chiakariga",
      "Chogoria",
      "Ganga",
      "Gatunga",
      "Igambang'Ombe",
      "Karingani",
      "Magumoni",
      "Mariani",
      "Marimanti",
      "Mitheru",
      "Mugwe",
      "Mukothima",
      "Muthambi",
      "Mwimbi",
      "Nkondi"
    ]
  },
  {
    "County": "Embu",
    "Wards": [
      "Central  Ward",
      "Evurore",
      "Gaturi North",
      "Gaturi South",
      "Kagaari North",
      "Kagaari South",
      "Kiambere",
      "Kirimari",
      "Kithimu",
      "Kyeni North",
      "Kyeni South",
      "Makima",
      "Mavuria",
      "Mbeti North",
      "Mbeti South",
      "Muminji",
      "Mwea",
      "Nginda",
      "Nthawa",
      "Ruguru/Ngandori"
    ]
  },
  {
    "County": "Kitui",
    "Wards": [
      "Athi",
      "Central",
      "Chuluni",
      "Endau/Malalani",
      "Ikanga/Kyatune",
      "Ikutha",
      "Kanyangi",
      "Kanziko",
      "Kiomo/Kyethani",
      "Kisasi",
      "Kivou",
      "Kwavonza/Yatta",
      "Kyangwithya East",
      "Kyangwithya West",
      "Kyome/Thaana",
      "Kyuso",
      "Mbitini",
      "Miambani",
      "Migwani",
      "Mui",
      "Mulango",
      "Mumoni",
      "Mutha",
      "Mutito/Kaliku",
      "Mutomo",
      "Ngomeni",
      "Nguni",
      "Nguutani",
      "Nuu",
      "Nzambani",
      "Tharaka",
      "Township",
      "Tseikuru",
      "Voo/Kyamatu",
      "Waita",
      "Zombe/Mwitika"
    ]
  },
  {
    "County": "Machakos",
    "Wards": [
      "Athi River",
      "Ekalakala",
      "Ikombe",
      "Kalama",
      "Kangundo Central",
      "Kangundo East",
      "Kangundo North",
      "Kangundo West",
      "Katangi",
      "Kathiani Central",
      "Kibauni",
      "Kinanie",
      "Kithimani",
      "Kivaa",
      "Kola",
      "Kyeleni",
      "Lower Kaewa/Kaani",
      "Machakos Central",
      "Makutano/ Mwala",
      "Masii",
      "Masinga Central",
      "Matungulu East",
      "Matungulu North",
      "Matungulu West",
      "Matuu",
      "Mbiuni",
      "Mitaboni",
      "Mua",
      "Mumbuni North",
      "Muthesya",
      "Muthetheni",
      "Muthwani",
      "Mutituni",
      "Muvuti/Kiima-Kimwe",
      "Ndalani",
      "Ndithini",
      "Syokimau/Mulolongo",
      "Tala",
      "Upper Kaewa/Iveti",
      "Wamunyu"
    ]
  },
  {
    "County": "Makueni",
    "Wards": [
      "Emali/Mulala",
      "Ilima",
      "Ivingoni/Nzambani",
      "Kalawa",
      "Kasikeu",
      "Kathonzweni",
      "Kee",
      "Kiima Kiu/Kalanzoni",
      "Kikumbulyu North",
      "Kikumbulyu South",
      "Kilungu",
      "Kisau/Kiteta",
      "Kithungo/Kitundu",
      "Kitise/Kithuki",
      "Makindu",
      "Masongaleni",
      "Mavindini",
      "Mbitini",
      "Mbooni",
      "Mtito Andei",
      "Mukaa",
      "Muvau/Kikuumini",
      "Nguu/Masumba",
      "Nguumo",
      "Nzaui/Kilili/Kalamba",
      "Thange",
      "Tulimani",
      "Ukia",
      "Waia/Kako",
      "Wote"
    ]
  },
  {
    "County": "Nyandarua",
    "Wards": [
      "Central",
      "Charagita",
      "Engineer",
      "Gathanji",
      "Gathara",
      "Gatimu",
      "Geta",
      "Githabai",
      "Githioro",
      "Kaimbaga",
      "Kanjuiri Ridge",
      "Karau",
      "Kipipiri",
      "Kiriita",
      "Leshau Pondo",
      "Magumu",
      "Mirangine",
      "Murungaru",
      "Njabini\\Kiburu",
      "North Kinangop",
      "Nyakio",
      "Rurii",
      "Shamata",
      "Wanjohi",
      "Weru"
    ]
  },
  {
    "County": "Nyeri",
    "Wards": [
      "Aguthi/Gaaki",
      "Chinga",
      "Dedan Kimanthi",
      "Gakawa",
      "Gatarakwa",
      "Gatitu/Muruguru",
      "Gikondi",
      "Iria-Ini",
      "Iriaini",
      "Kabaru",
      "Kamakwa/Mukaro",
      "Karatina Town",
      "Karima",
      "Kiganjo/Mathari",
      "Kirimukuyu",
      "Konyu",
      "Magutu",
      "Mahiga",
      "Mugunda",
      "Mukurwe-Ini Central",
      "Mukurwe-Ini West",
      "Mweiga",
      "Mwiyogo/Endarasha",
      "Naromoru Kiamathaga",
      "Rugi",
      "Ruguru",
      "Ruring'U",
      "Rware",
      "Thegu River",
      "Wamagana"
    ]
  },
  {
    "County": "Kirinyaga",
    "Wards": [
      "Baragwi",
      "Gathigiriri",
      "Inoi",
      "Kabare",
      "Kangai",
      "Kanyeki-Ini",
      "Kariti",
      "Karumandi",
      "Kerugoya",
      "Kiine",
      "Mukure",
      "Murinduko",
      "Mutira",
      "Mutithi",
      "Ngariama",
      "Njukiini",
      "Nyangati",
      "Tebere",
      "Thiba",
      "Wamumu"
    ]
  },
  {
    "County": "Murang'A",
    "Wards": [
      "Gaichanjiru",
      "Gatanga",
      "Gaturi",
      "Gitugi",
      "Ichagaki",
      "Ithanga",
      "Ithiru",
      "Kagundu-Ini",
      "Kahumbu",
      "Kakuzi/Mitubiri",
      "Kamacharia",
      "Kamahuha",
      "Kambiti",
      "Kangari",
      "Kanyenyaini",
      "Kariara",
      "Kigumo",
      "Kihumbu-Ini",
      "Kimorori/Wempa",
      "Kinyona",
      "Kiru",
      "Makuyu",
      "Mbiri",
      "Mugoiri",
      "Mugumo-Ini",
      "Muguru",
      "Murarandia",
      "Muruka",
      "Muthithi",
      "Ng'Araria",
      "Nginda",
      "Ruchu",
      "Rwathia",
      "Township",
      "Wangu"
    ]
  },
  {
    "County": "Kiambu",
    "Wards": [
      "Biashara",
      "Bibirioni",
      "Chania",
      "Cianda",
      "Gatongora",
      "Gatuanyaga",
      "Gitaru",
      "Githiga",
      "Githobokoni",
      "Githunguri",
      "Gitothua",
      "Gituamba",
      "Hospital",
      "Ikinu",
      "Juja",
      "Kabete",
      "Kahawa Sukari",
      "Kahawa Wendani",
      "Kalimoni",
      "Kamburu",
      "Kamenu",
      "Karai",
      "Karuri",
      "Kiamwangi",
      "Kiganjo",
      "Kihara",
      "Kijabe",
      "Kikuyu",
      "Kinale",
      "Kinoo",
      "Kiuu",
      "Komothai",
      "Lari/Kirenga",
      "Limuru Central",
      "Limuru East",
      "Mang'U",
      "Muchatha",
      "Muguga",
      "Murera",
      "Mwihoko",
      "Mwiki",
      "Nachu",
      "Ndarugu",
      "Ndeiya",
      "Ndenderu",
      "Ndumberi",
      "Ngecha Tigoni",
      "Ngenda",
      "Ngewa",
      "Ngoliba",
      "Nyadhuna",
      "Nyanduma",
      "Riabai",
      "Sigona",
      "Theta",
      "Ting'Ang'A",
      "Township",
      "Uthiru",
      "Witeithie"
    ]
  },
  {
    "County": "Turkana",
    "Wards": [
      "Kaaleng/Kaikor",
      "Kaeris",
      "Kakuma",
      "Kalapata",
      "Kalobeyei",
      "Kalokol",
      "Kanamkemer",
      "Kang'Atotha",
      "Kapedo/Napeitom",
      "Kaputir",
      "Katilia",
      "Katilu",
      "Kerio Delta",
      "Kibish",
      "Kotaruk/Lobei",
      "Lake Zone",
      "Lapur",
      "Letea",
      "Lobokat",
      "Lodwar Township",
      "Loima",
      "Lokichar",
      "Lokichoggio",
      "Lokiriama/Lorengippi",
      "Lokori/Kochodin",
      "Lopur",
      "Nakalale",
      "Nanaam",
      "Songot",
      "Turkwel"
    ]
  },
  {
    "County": "West Pokot",
    "Wards": [
      "Alale",
      "Batei",
      "Chepareria",
      "Endugh",
      "Kapckok",
      "Kapenguria",
      "Kasei",
      "Kiwawa",
      "Kodich",
      "Lelan",
      "Lomut",
      "Masool",
      "Mnagei",
      "Riwo",
      "Sekerr",
      "Siyoi",
      "Sook",
      "Suam",
      "Tapach",
      "Weiwei"
    ]
  },
  {
    "County": "Samburu",
    "Wards": [
      "Angata Nanyokie",
      "Baawa",
      "El-Barta",
      "Lodokejek",
      "Loosuk",
      "Maralal",
      "Nachola",
      "Ndoto",
      "Nyiro",
      "Poro",
      "Suguta Marmar",
      "Wamba East",
      "Wamba North",
      "Wamba West",
      "Waso"
    ]
  },
  {
    "County": "Trans Nzoia",
    "Wards": [
      "Bidii",
      "Chepchoina",
      "Chepsiro/Kiptoror",
      "Cherangany/Suwerwa",
      "Endebess",
      "Hospital",
      "Kaplamai",
      "Kapomboi",
      "Keiyo",
      "Kiminini",
      "Kinyoro",
      "Kwanza",
      "Machewa",
      "Makutano",
      "Matisi",
      "Matumbei",
      "Motosiet",
      "Nabiswa",
      "Saboti",
      "Sikhendu",
      "Sinyerere",
      "Sirende",
      "Sitatunga",
      "Tuwani",
      "Waitaluk"
    ]
  },
  {
    "County": "Uasin Gishu",
    "Wards": [
      "Ainabkoi/Olare",
      "Cheptiret/Kipchamo",
      "Huruma",
      "Kamagut",
      "Kapkures",
      "Kapsaos",
      "Kapsoya",
      "Kaptagat",
      "Karuna/Meibeki",
      "Kimumu",
      "Kipkenyo",
      "Kiplombe",
      "Kipsomba",
      "Kuinet/Kapsuswa",
      "Langas",
      "Megun",
      "Moi'S Bridge",
      "Moiben",
      "Ngenyilel",
      "Ngeria",
      "Racecourse",
      "Segero/Barsombe",
      "Sergoit",
      "Simat/Kapseret",
      "Soy",
      "Tapsagoi",
      "Tarakwa",
      "Tembelio",
      "Tulwet/Chuiyat",
      "Ziwa"
    ]
  },
  {
    "County": "Elgeyo/Marakwet",
    "Wards": [
      "Arror",
      "Chepkorio",
      "Cherang'Any/Chebororwa",
      "Embobut / Embulot",
      "Emsoo",
      "Endo",
      "Kabiemit",
      "Kamariny",
      "Kapchemutwa",
      "Kapsowar",
      "Kaptarakwa",
      "Kapyego",
      "Lelan",
      "Metkei",
      "Moiben/Kuserwo",
      "Sambirir",
      "Sengwer",
      "Soy North",
      "Soy South",
      "Tambach"
    ]
  },
  {
    "County": "Nandi",
    "Wards": [
      "Chemelil/Chemase",
      "Chemundu/Kapng'Etuny",
      "Chepkumia",
      "Chepkunyuk",
      "Chepterwai",
      "Kabisaga",
      "Kabiyet",
      "Kabwareng",
      "Kapchorua",
      "Kapkangani",
      "Kapsabet",
      "Kapsimotwo",
      "Kaptel/Kamoiywo",
      "Kaptumo-Kaboi",
      "Kemeloi-Maraba",
      "Kilibwoni",
      "Kipkaren",
      "Kiptuya",
      "Kobujoi",
      "Kosirai",
      "Koyo-Ndurio",
      "Kurgung/Surungai",
      "Lelmokwo/Ngechek",
      "Nandi Hills",
      "Ndalat",
      "Ol'Lessos",
      "Sangalo/Kebulonik",
      "Songhor/Soba",
      "Terik",
      "Tindiret"
    ]
  },
  {
    "County": "Baringo",
    "Wards": [
      "Churo/Amaya",
      "Emining",
      "Ewalel Chapchap",
      "Ilchamus",
      "Kabarnet",
      "Kapropita",
      "Kisanana",
      "Koibatek",
      "Kolowa",
      "Lembus",
      "Lembus Kwen",
      "Lembus/Perkerra",
      "Loiyamorock",
      "Marigat",
      "Mochongoi",
      "Mogotio",
      "Mukutani",
      "Mumberes/Maji Mazuri",
      "Ravine",
      "Ribkwo",
      "Sacho",
      "Silale",
      "Tangulbei/Korossi",
      "Tenges",
      "Tirioko"
    ]
  },
  {
    "County": "Laikipia",
    "Wards": [
      "Igwamiti",
      "Kinamba",
      "Marmanet",
      "Mukogondo East",
      "Mukogondo West",
      "Nanyuki",
      "Ngobit",
      "Olmoran",
      "Rumuruti Township",
      "Salama",
      "Segera",
      "Sosian",
      "Thingithu",
      "Tigithi",
      "Umande"
    ]
  },
  {
    "County": "Nakuru",
    "Wards": [
      "Amalo",
      "Bahati",
      "Barut",
      "Biashara",
      "Dundori",
      "Elburgon",
      "Elementaita",
      "Flamingo",
      "Gilgil",
      "Hells Gate",
      "Kabatini",
      "Kabazi",
      "Kapkures",
      "Kaptembwo",
      "Keringet",
      "Kiamaina",
      "Kihingo",
      "Kiptagich",
      "Kivumbini",
      "Lakeview",
      "Lanet/Umoja",
      "Lare",
      "London",
      "Maai-Mahiu",
      "Maiella",
      "Malewa West",
      "Mariashoni",
      "Mauche",
      "Maunarok",
      "Mbaruk/Eburu",
      "Menengai",
      "Menengai West",
      "Molo",
      "Mosop",
      "Murindati",
      "Naivasha East",
      "Nakuru East",
      "Nessuit",
      "Njoro",
      "Olkaria",
      "Rhoda",
      "Shaabab",
      "Soin",
      "Solai",
      "Subukia",
      "Tinet",
      "Turi",
      "Visoi",
      "Viwandani",
      "Waseges"
    ]
  },
  {
    "County": "Narok",
    "Wards": [
      "Angata Barikoi",
      "Ildamat",
      "Ilkerin",
      "Ilmotiok",
      "Kapsasian",
      "Keekonyokie",
      "Keyian",
      "Kilgoris Central",
      "Kimintet",
      "Loita",
      "Lolgorian",
      "Majimoto/Naroosura",
      "Mara",
      "Melelo",
      "Melili",
      "Mogondo",
      "Mosiro",
      "Naikarra",
      "Narok Town",
      "Nkareta",
      "Olokurto",
      "Ololmasani",
      "Ololulung'A",
      "Olorropil",
      "Olpusimoru",
      "Sagamian",
      "Shankoe",
      "Siana",
      "Sogoo",
      "Suswa"
    ]
  },
  {
    "County": "Kajiado",
    "Wards": [
      "Dalalekutuk",
      "Entonet/Lenkisim",
      "Ewuaso Oonkidong'I",
      "Ildamat",
      "Iloodokilani",
      "Imaroro",
      "Kaputiei North",
      "Keekonyokie",
      "Kenyawa-Poka",
      "Kimana",
      "Kitengela",
      "Kuku",
      "Magadi",
      "Matapato North",
      "Matapato South",
      "Mbirikani/Eselenkei",
      "Mosiro",
      "Ngong",
      "Nkaimurunya",
      "Olkeri",
      "Oloolua",
      "Oloosirkon/Sholinke",
      "Ongata Rongai",
      "Purko",
      "Rombo"
    ]
  },
  {
    "County": "Kericho",
    "Wards": [
      "Ainamoi",
      "Chaik",
      "Cheboin",
      "Chemosot",
      "Cheplanget",
      "Chepseon",
      "Cheptororiet/Seretut",
      "Chilchila",
      "Kabianga",
      "Kamasian",
      "Kapkatet",
      "Kapkugerwet",
      "Kaplelartet",
      "Kapsaos",
      "Kapsoit",
      "Kapsuser",
      "Kedowa/Kimugul",
      "Kipchebor",
      "Kipchimchim",
      "Kipkelion",
      "Kisiara",
      "Kunyak",
      "Litein",
      "Londiani",
      "Sigowet",
      "Soin",
      "Soliat",
      "Tebesonik",
      "Tendeno/Sorget",
      "Waldai"
    ]
  },
  {
    "County": "Bomet",
    "Wards": [
      "Boito",
      "Chebunyo",
      "Chemagel",
      "Chemaner",
      "Chepchabas",
      "Chesoen",
      "Embomos",
      "Kapletundo",
      "Kembu",
      "Kimulot",
      "Kipreres",
      "Kipsonoi",
      "Kong'Asis",
      "Longisa",
      "Merigi",
      "Mogogosiek",
      "Mutarakwa",
      "Ndanai/Abosi",
      "Ndaraweta",
      "Nyangores",
      "Rongena/Manaret",
      "Sigor",
      "Silibwet Township",
      "Singorwet",
      "Siongiroi"
    ]
  },
  {
    "County": "Kakamega",
    "Wards": [
      "Bunyala Central",
      "Bunyala East",
      "Bunyala West",
      "Butali/Chegulo",
      "Butsotso Central",
      "Butsotso East",
      "Butsotso South",
      "Chekalini",
      "Chemuche",
      "Chevaywa",
      "East Kabras",
      "Etenje",
      "Idakho Central",
      "Idakho East",
      "Idakho North",
      "Idakho South",
      "Ingostse-Mathia",
      "Isukha Central",
      "Isukha East",
      "Isukha North",
      "Isukha South",
      "Isukha West",
      "Khalaba",
      "Kholera",
      "Kisa Central",
      "Kisa East",
      "Kisa North",
      "Kisa West",
      "Kongoni",
      "Koyonzo",
      "Likuyani",
      "Lugari",
      "Lumakanda",
      "Lwandeti",
      "Mahiakalo",
      "Manda-Shivanga",
      "Marama Central",
      "Marama North",
      "Marama South",
      "Marama West",
      "Marenyo - Shianda",
      "Mautuma",
      "Mayoni",
      "Mumias Central",
      "Mumias North",
      "Murhanda",
      "Musanda",
      "Namamali",
      "Nzoia",
      "Sango",
      "Sheywe",
      "Shinoyi-Shikomari-",
      "Shirere",
      "Shirugu-Mugai",
      "Sinoko",
      "South Kabras",
      "West Kabras"
    ]
  },
  {
    "County": "Vihiga",
    "Wards": [
      "Banja",
      "Busali",
      "Central Bunyore",
      "Central Maragoli",
      "Chavakali",
      "Emabungo",
      "Gisambai",
      "Jepkoyai",
      "Luanda South",
      "Luanda Township",
      "Lugaga-Wamuluma",
      "Lyaduywa/Izava",
      "Muhudu",
      "Mungoma",
      "Mwibona",
      "North East Bunyore",
      "North Maragoli",
      "Shamakhokho",
      "Shiru",
      "South Maragoli",
      "Tambua",
      "Wemilabi",
      "West Bunyore",
      "West Sabatia",
      "Wodanga"
    ]
  },
  {
    "County": "Bungoma",
    "Wards": [
      "Bokoli",
      "Bumula",
      "Bwake/Luuya",
      "Cheptais",
      "Chepyuk",
      "Chesikaki",
      "Elgon",
      "Kabuchai/Chwele",
      "Kabula",
      "Kamukuywa",
      "Kapkateny",
      "Kaptama",
      "Khasoko",
      "Kibingei",
      "Kimaeti",
      "Kimilili",
      "Lwandanyi",
      "Maeni",
      "Malakisi/South Kulisiru",
      "Maraka",
      "Matulo",
      "Mbakalo",
      "Mihuu",
      "Milima",
      "Misikhu",
      "Mukuyuni",
      "Naitiri/Kabuyefwe",
      "Namwela",
      "Ndalu/ Tabani",
      "Ndivisi",
      "Siboti",
      "Sitikho",
      "South Bukusu",
      "Soysambu/ Mitua",
      "Tongaren",
      "West Bukusu",
      "West Nalondo"
    ]
  },
  {
    "County": "Busia",
    "Wards": [
      "Ageng'A Nanguba",
      "Amukura Central",
      "Amukura East",
      "Amukura West",
      "Ang'Orom",
      "Ang'Urai East",
      "Ang'Urai North",
      "Ang'Urai South",
      "Bukhayo Central",
      "Bukhayo East",
      "Bukhayo North/Waltsi",
      "Bukhayo West",
      "Bunyala Central",
      "Bunyala North",
      "Bunyala South",
      "Bunyala West",
      "Burumba",
      "Busibwabo",
      "Bwiri",
      "Chakol North",
      "Chakol South",
      "Elugulu",
      "Kingandole",
      "Malaba Central",
      "Malaba North",
      "Malaba South",
      "Marachi Central",
      "Marachi East",
      "Marachi North",
      "Marachi West",
      "Matayos South",
      "Mayenje",
      "Nambale Township",
      "Namboboto Nambuku",
      "Nangina"
    ]
  },
  {
    "County": "Siaya",
    "Wards": [
      "Central Alego",
      "Central Gem",
      "Central Sakwa",
      "East Gem",
      "East Ugenya",
      "North Alego",
      "North Gem",
      "North Sakwa",
      "North Ugenya",
      "Siaya Township",
      "South East Alego",
      "South Gem",
      "South Sakwa",
      "Ukwala",
      "Usonga",
      "West Alego",
      "West Gem",
      "West Sakwa",
      "West Ugenya",
      "West Yimbo",
      "Yala Township",
      "Yimbo East"
    ]
  },
  {
    "County": "Kisumu",
    "Wards": [
      "Ahero",
      "Awasi/Onjiko",
      "Central Kisumu",
      "Central Nyakach",
      "Central Seme",
      "Chemelil",
      "East Kano/Wawidhi",
      "East Seme",
      "Kabonyo/Kanyagwal",
      "Kajulu",
      "Kisumu North",
      "Kobura",
      "Kolwa Central",
      "Kolwa East",
      "Kondele",
      "Manyatta 'B'",
      "Market Milimani",
      "Masogo/Nyang'Oma",
      "Migosi",
      "Miwani",
      "Muhoroni/Koru",
      "North Nyakach",
      "North Seme",
      "North West Kisumu",
      "Nyalenda 'A'",
      "Nyalenda B",
      "Ombeyi",
      "Railways",
      "Shaurimoyo Kaloleni",
      "South East Nyakach",
      "South West Kisumu",
      "South West Nyakach",
      "West Kisumu",
      "West Nyakach",
      "West Seme"
    ]
  },
  {
    "County": "Homa Bay",
    "Wards": [
      "Central",
      "Central Kasipul",
      "East Gem",
      "East Kamagak",
      "Gembe",
      "Gwassi North",
      "Gwassi South",
      "Homa Bay Arujo",
      "Homa Bay Central",
      "Homa Bay East",
      "Homa Bay West",
      "Kabondo East",
      "Kabondo West",
      "Kabuoch South/Pala",
      "Kagan",
      "Kaksingri West",
      "Kanyadoto",
      "Kanyaluo",
      "Kanyamwa Kologi",
      "Kanyamwa Kosewe",
      "Kanyikela",
      "Kasgunga",
      "Kendu Bay Town",
      "Kibiri",
      "Kochia",
      "Kojwach",
      "Kokwanyo/Kakelo",
      "Kwabwai",
      "Lambwe",
      "Mfangano Island",
      "North Kabuoch",
      "North Karachuonyo",
      "Ruma Kaksingri East",
      "Rusinga Island",
      "South Kasipul",
      "Wangchieng",
      "West Gem",
      "West Kamagak",
      "West Karachuonyo",
      "West Kasipul"
    ]
  },
  {
    "County": "Migori",
    "Wards": [
      "Bukira Centrl/Ikerege",
      "Bukira East",
      "Central Kamagambo",
      "Central Kanyamkago",
      "Central Sakwa",
      "East Kamagambo",
      "East Kanyamkago",
      "God Jope",
      "Gokeharaka/Getambwega",
      "Got Kachola",
      "Isibania",
      "Kachien'G",
      "Kakrao",
      "Kaler",
      "Kanyasa",
      "Kwa",
      "Macalder/Kanyarwanda",
      "Makerero",
      "Masaba",
      "Muhuru",
      "North Kadem",
      "North Kamagambo",
      "North Kanyamkago",
      "North Sakwa",
      "Ntimaru East",
      "Ntimaru West",
      "Nyabasi East",
      "Nyabasi West",
      "Nyamosense/Komosoko",
      "Ragana-Oruba",
      "South Kamagambo",
      "South Kanyamkago",
      "South Sakwa",
      "Suna Central",
      "Tagare",
      "Wasimbete",
      "Wasweta Ii",
      "West Kanyamkago",
      "West Sakwa",
      "Wiga"
    ]
  },
  {
    "County": "Kisii",
    "Wards": [
      "Birongo",
      "Bobaracho",
      "Bobasi Bogetaorio",
      "Bobasi Boitangare",
      "Bobasi Central",
      "Bobasi Chache",
      "Bogeka",
      "Bogetenga",
      "Bogiakumu",
      "Bogusero",
      "Boikang'A",
      "Bomariba",
      "Bomorenda",
      "Borabu / Chitago",
      "Gesusu",
      "Getenga",
      "Ibeno",
      "Ichuni",
      "Kegogi",
      "Keumbu",
      "Kiamokama",
      "Kiogoro",
      "Kisii Central",
      "Kitutu   Central",
      "Marani",
      "Masige East",
      "Masige West",
      "Masimba",
      "Monyerero",
      "Moticho",
      "Nyacheki",
      "Nyakoe",
      "Nyamasibi",
      "Nyatieko",
      "Riana",
      "Sameta/Mokwerero",
      "Sensi",
      "Tabaka"
    ]
  },
  {
    "County": "Nyamira",
    "Wards": [
      "Bogichora",
      "Bokeira",
      "Bomwagamo",
      "Bonyamatuta",
      "Bosamaro",
      "Ekerenyo",
      "Esise",
      "Gachuba",
      "Gesima",
      "Itibo",
      "Kemera",
      "Kiabonyoru",
      "Magombo",
      "Magwagwa",
      "Manga",
      "Mekenene",
      "Nyamaiya",
      "Nyansiongo",
      "Rigoma",
      "Township"
    ]
  },
  {
    "County": "Nairobi",
    "Wards": [
      "Airbase",
      "Baba Dogo",
      "California",
      "Claycity",
      "Dandora Area I",
      "Dandora Area Ii",
      "Dandora Area Iii",
      "Dandora Area Iv",
      "Eastleigh North",
      "Eastleigh South",
      "Embakasi",
      "Gatina",
      "Githurai",
      "Harambee",
      "Hospital",
      "Huruma",
      "Imara Daima",
      "Kabiro",
      "Kahawa",
      "Kahawa West",
      "Kangemi",
      "Karen",
      "Kariobangi North",
      "Kariobangi South",
      "Karura",
      "Kasarani",
      "Kawangware",
      "Kayole Central",
      "Kayole North",
      "Kayole South",
      "Kiamaiko",
      "Kileleshwa",
      "Kilimani",
      "Kitisuru",
      "Komarock",
      "Korogocho",
      "Kwa Njenga",
      "Kwa Reuben",
      "Kware",
      "Laini Saba",
      "Landimawe",
      "Lindi",
      "Lower Savannah",
      "Lucky Summer",
      "Mabatini",
      "Makina",
      "Makongeni",
      "Maringo/Hamza",
      "Mathare North",
      "Matopeni",
      "Mihango",
      "Mlango Kubwa",
      "Mountain View",
      "Mowlem",
      "Mugumo-Ini",
      "Mutuini",
      "Mwiki",
      "Nairobi Central",
      "Nairobi South",
      "Nairobi West",
      "Ngando",
      "Ngara",
      "Ngei",
      "Njiru",
      "Nyayo Highrise",
      "Pangani",
      "Parklands/Highridge",
      "Pipeline",
      "Pumwani",
      "Riruta",
      "Roysambu",
      "Ruai",
      "Sarangombe",
      "South-C",
      "Umoja I",
      "Umoja Ii",
      "Upper Savannah",
      "Utalii",
      "Utawala",
      "Uthiru/Ruthimitu",
      "Viwandani",
      "Waithaka",
      "Woodley/Kenyatta Golf",
      "Zimmerman",
      "Ziwani/Kariokor"
    ]
  }
]